dpt_plugins/__init__.py
dpt_plugins/hook.py
dpt_plugins/hook_context.py
dpt_plugins/hookable_settings.py
dpt_plugins/manager.py
dpt_plugins/weakref_method.py
dpt_plugins-1.0.4.data/data/docs/LICENSE
dpt_plugins-1.0.4.data/data/docs/README
dpt_plugins-1.0.4.dist-info/LICENSE
dpt_plugins-1.0.4.dist-info/METADATA
dpt_plugins-1.0.4.dist-info/WHEEL
dpt_plugins-1.0.4.dist-info/top_level.txt
dpt_plugins-1.0.4.dist-info/RECORD
